{"minVersion":"0.1","headerImage":"https://repo.ginsu.dev/assets/com.ginsu.weatherls/banner.png","tintColor":"#55c6d3","tabs":[{"tabname":"Details","views":[{"class":"DepictionScreenshotsView","screenshots":[{"url":"https://repo.ginsu.dev/assets/com.ginsu.weatherls/screenshot/screenshot1.jpg","accessibilityText":"Screenshot"}],"itemCornerRadius":8,"itemSize":"{185,400}"},{"markdown":"[![Build Status](https://travis-ci.org/joemccann/dillinger.svg?branch=master)](https://travis-ci.org/joemccann/dillinger)\n# WeatherLS\n###### _Quick weather access_\n\nWeatherLS shows you the current weather conditions and temperature on the lock screen.\n","useSpacing":"true","class":"DepictionMarkdownView"},{"class":"DepictionSpacerView"},{"class":"DepictionHeaderView","title":"Information"},{"class":"DepictionTableTextView","title":"Developer","text":"Ginsu"},{"class":"DepictionTableTextView","title":"Version","text":"2.0.1"},{"class":"DepictionTableTextView","title":"Compatibility","text":"iOS 14.0 to 15.0"},{"class":"DepictionTableTextView","title":"Section","text":"Tweaks"},{"class":"DepictionSpacerView"},{"class":"DepictionTableButtonView","title":"Contact Support","action":"depiction-https://repo.ginsu.dev/depiction/native/help/com.ginsu.weatherls.json","openExternal":"true","tintColor":"#55c6d3"},{"class":"DepictionLabelView","text":"Ginsu Tweaks | Silica 1.2.2","textColor":"#999999","fontSize":"10.0","alignment":1}],"class":"DepictionStackView"},{"tabname":"Changelog","views":[{"class":"DepictionMarkdownView","markdown":"#### Version 2.0.1\n\n- The temperature label will now automatically adjust it's colour depending on light/dark wallpapers."},{"class":"DepictionLabelView","text":"Ginsu Tweaks | Silica 1.2.2","textColor":"#999999","fontSize":"10.0","alignment":1}],"class":"DepictionStackView"}],"class":"DepictionTabView"}